nikki_utils/__init__.py
nikki_utils/nlogging.py
nikki_utils-0.0.14.dist-info/licenses/LICENSE
nikki_utils-0.0.14.dist-info/METADATA
nikki_utils-0.0.14.dist-info/WHEEL
nikki_utils-0.0.14.dist-info/top_level.txt
nikki_utils-0.0.14.dist-info/RECORD
