Metadata-Version: 2.4
Name: nikki-utils
Version: 0.0.14
Summary: Simple utils I use across many of my Python projects
Author-email: Nikki Hess <nkhess@umich.edu>
License-Expression: MIT
Project-URL: Homepage, https://github.com/nikkihess/nikki-utils
Project-URL: Issues, https://github.com/nikkihess/nikki-utils/issues
Classifier: Programming Language :: Python :: 3.10
Classifier: Programming Language :: Python :: 3.11
Classifier: Programming Language :: Python :: 3.12
Classifier: Programming Language :: Python :: 3.13
Classifier: Programming Language :: Python :: 3.14
Classifier: Operating System :: OS Independent
Requires-Python: >=3.10
License-File: LICENSE
Dynamic: license-file
